box_intersect_lib_py-0.8.5.dist-info/METADATA
box_intersect_lib_py-0.8.5.dist-info/WHEEL
box_intersect_lib_py-0.8.5.dist-info/licenses/LICENSE.txt
box_intersect_lib_py/__init__.py
box_intersect_lib_py/box_intersect_lib_py.cp311-win_amd64.pyd
box_intersect_lib_py-0.8.5.dist-info/RECORD
