Metadata-Version: 2.4
Name: box-intersect-lib-py
Version: 0.8.5
Classifier: Programming Language :: Rust
Classifier: Programming Language :: Python :: Implementation :: CPython
License-File: LICENSE.txt
Summary: Box intersection/overlap/density algorithms in Rust with python bindings.
Keywords: box,algorithm,rust,python,pyo3
Requires-Python: >=3.8
Project-URL: Homepage, https://github.com/Techcyte/box-intersect-lib
Project-URL: Repository, https://github.com/Techcyte/box-intersect-lib.git
